pycalver/__init__.py
pycalver/__main__.py
pycalver/cli.py
pycalver/config.py
pycalver/lex_id.py
pycalver/parse.py
pycalver/patterns.py
pycalver/rewrite.py
pycalver/vcs.py
pycalver/version.py
pycalver-202010.1043.dist-info/LICENSE
pycalver-202010.1043.dist-info/METADATA
pycalver-202010.1043.dist-info/WHEEL
pycalver-202010.1043.dist-info/entry_points.txt
pycalver-202010.1043.dist-info/top_level.txt
pycalver-202010.1043.dist-info/zip-safe
pycalver-202010.1043.dist-info/RECORD
