Metadata-Version: 2.1
Name: pycalver
Version: 202010.1043
Summary: CalVer for python libraries.
Home-page: https://gitlab.com/mbarkhau/pycalver
Author: Manuel Barkhau
Author-email: mbarkhau@gmail.com
License: MIT
Keywords: version versioning bumpversion calver
Platform: UNKNOWN
Classifier: Development Status :: 4 - Beta
Classifier: Environment :: Console
Classifier: Environment :: Other Environment
Classifier: Intended Audience :: Developers
Classifier: License :: OSI Approved :: MIT License
Classifier: Operating System :: Unix
Classifier: Operating System :: POSIX
Classifier: Operating System :: Microsoft :: Windows
Classifier: Operating System :: MacOS :: MacOS X
Classifier: Programming Language :: Python
Classifier: Programming Language :: Python :: 2.7
Classifier: Programming Language :: Python :: 3
Classifier: Programming Language :: Python :: Implementation :: CPython
Classifier: Programming Language :: Python :: Implementation :: PyPy
Classifier: Topic :: Software Development :: Libraries
Classifier: Topic :: Software Development :: Libraries :: Python Modules
Requires-Dist: pathlib2
Requires-Dist: click
Requires-Dist: toml
Requires-Dist: six
Requires-Dist: typing ; python_version < "3.5"
